anthropic_admin/__init__.py
anthropic_admin/client.py
anthropic_admin/exceptions.py
anthropic_admin/models/__init__.py
anthropic_admin/models/api_keys.py
anthropic_admin/models/base.py
anthropic_admin/models/invites.py
anthropic_admin/models/members.py
anthropic_admin/models/workspaces.py
anthropic_admin/resources/__init__.py
anthropic_admin/resources/api_keys.py
anthropic_admin/resources/base.py
anthropic_admin/resources/invites.py
anthropic_admin/resources/members.py
anthropic_admin/resources/workspaces.py
anthropic_admin/utils/__init__.py
anthropic_admin/utils/http.py
anthropic_admin/utils/validation.py
anthropic_admin-0.1.0.dist-info/licenses/LICENSE
anthropic_admin-0.1.0.dist-info/METADATA
anthropic_admin-0.1.0.dist-info/WHEEL
anthropic_admin-0.1.0.dist-info/top_level.txt
anthropic_admin-0.1.0.dist-info/RECORD
